annonex2embl/Annonex2emblMain.py
annonex2embl/CLIOps.py
annonex2embl/CheckingOps.py
annonex2embl/DegappingOps.py
annonex2embl/GenerationOps.py
annonex2embl/GlobalVariables.py
annonex2embl/IOOps.py
annonex2embl/ParsingOps.py
annonex2embl/__init__.py
annonex2embl-1.0.3.data/scripts/annonex2embl_launcher_CLI.py
annonex2embl-1.0.3.dist-info/AUTHORS
annonex2embl-1.0.3.dist-info/LICENSE
annonex2embl-1.0.3.dist-info/METADATA
annonex2embl-1.0.3.dist-info/WHEEL
annonex2embl-1.0.3.dist-info/entry_points.txt
annonex2embl-1.0.3.dist-info/top_level.txt
annonex2embl-1.0.3.dist-info/RECORD
