Metadata-Version: 2.1
Name: annonex2embl
Version: 1.0.3
Summary: Converts an annotated DNA multi-sequence alignment (in NEXUS format) to an EMBL flatfile for submission to ENA via the Webin-CLI submission tool
Home-page: https://github.com/michaelgruenstaeudl/annonex2embl
Author: Michael Gruenstaeudl, PhD
Author-email: m.gruenstaeudl@fu-berlin.de
License: BSD
Keywords: novel DNA sequences,public sequence databases,European Nucleotide Archive,file conversion,flatfile
Platform: UNKNOWN
Classifier: Development Status :: 4 - Beta
Classifier: License :: OSI Approved :: BSD License
Classifier: Programming Language :: Python :: 3.7
Classifier: Intended Audience :: Science/Research
Classifier: Topic :: Scientific/Engineering :: Bio-Informatics
Requires-Dist: biopython (<=1.77)
Requires-Dist: argparse
Requires-Dist: requests
Requires-Dist: unidecode
